pyread_eagle/__init__.py
pyread_eagle/__version__.py
pyread_eagle/_pyread_eagle.py
pyread_eagle-1.0.3.dist-info/LICENSE.md
pyread_eagle-1.0.3.dist-info/METADATA
pyread_eagle-1.0.3.dist-info/WHEEL
pyread_eagle-1.0.3.dist-info/top_level.txt
pyread_eagle-1.0.3.dist-info/RECORD
