Metadata-Version: 2.1
Name: pyread-eagle
Version: 1.0.3
Summary: Pure-python port of J. Helly's read_eagle.
Author-email: Kyle Oman <kyle.a.oman@durham.ac.uk>
Project-URL: Homepage, https://github.com/kyleaoman/pyread_eagle
Project-URL: Bug Tracker, https://github.com/kyleaoman/pyread_eagle/issues
Classifier: Programming Language :: Python :: 3
Classifier: License :: OSI Approved :: GNU General Public License v3 (GPLv3)
Classifier: Operating System :: OS Independent
Requires-Python: >=3.7
License-File: LICENSE.md
Requires-Dist: numpy
Requires-Dist: h5py
